setup.cfg
setup.py
SDH_Metrics.egg-info/PKG-INFO
SDH_Metrics.egg-info/SOURCES.txt
SDH_Metrics.egg-info/dependency_links.txt
SDH_Metrics.egg-info/namespace_packages.txt
SDH_Metrics.egg-info/requires.txt
SDH_Metrics.egg-info/top_level.txt
sdh/__init__.py
sdh/metrics/__init__.py
sdh/metrics/jobs/__init__.py
sdh/metrics/jobs/calculus.py
sdh/metrics/server/__init__.py
sdh/metrics/store/__init__.py
sdh/metrics/store/fragment.py
sdh/metrics/store/metrics.py