Metadata-Version: 1.1
Name: SDH-Metrics
Version: 0.0.21
Summary: A library for making temporal information services for the SDH project.
Home-page: https://github.com/smartdeveloperhub/sdh-metrics
Author: Fernando Serena
Author-email: fernando.serena@centeropenmiddleware.com
License: Apache 2
Download-URL: https://github.com/smartdeveloperhub/sdh-metrics/tarball/0.2.2
Keywords: linked-data,ontology,path,sdh
Platform: UNKNOWN
